Workbook

Sheet Instruções
A1: Controle Semanal de KPIs — Vendas Disruptivas B2B
A2: Playbook Indústria de Móveis · Marketing + Vendas · Ritual de alinhamento semanal
A5: Como usar
A6: 1. Metas | B6: Defina as metas anuais/mensais na aba Metas (células amarelas = editar).
A7: 2. Semanal | B7: Toda semana, preencha uma nova linha na aba Semanal. Valores em azul são inputs; pretos são fórmulas.
A8: 3. Dashboard | B8: Acompanhe status vs meta, últimas 8 semanas e o ritual da ponte Mkt → Vendas.
A9: 4. Ritual | B9: Reunião de 30 min: Aceite de SQL · SLA de contato · Motivos de perda. Anote na coluna Observações.
A11: Legenda de cores
A12: Azul (números) | B12: Inputs — você digita
A13: Preto (números) | B13: Fórmulas — calculadas automaticamente
A14: Verde (números) | B14: Valores puxados de outra aba
A15: Amarelo | B15: Metas / células-chave para atualizar
A17: North Stars
A18: Marketing | B18: MQL → SQL > 40%
A19: Vendas | B19: SQL → Cliente > 30%
A20: Ponte | B20: Taxa de aceite de SQL > 80%
A22: Fonte | B22: Alinhado ao playbook_vendas_disruptivas_moveis_b2b.html · Julho 2026

Sheet Dashboard
A1: Dashboard Semanal — KPIs
A2: Última semana com dados preenchidos · Comparação automática com Metas
A4: Resumo da última semana
A5: Semana (início) | B5: =LOOKUP(2,1/(Semanal!E6:E21<>""),Semanal!B6:B21) | C5: até | D5: =LOOKUP(2,1/(Semanal!E6:E21<>""),Semanal!C6:C21)
A7: Área | B7: KPI | C7: Resultado | D7: Meta | E7: Δ vs Meta | F7: Status | G7: Direção
A8: Marketing | B8: MQL → SQL | C8: =IFERROR(LOOKUP(2,1/(Semanal!$E$6:$E$21<>""),Semanal!I$6:I$21),"") | D8: =Metas!E5 | E8: =IF(OR(C8="",D8=""),"",C8-D8) | F8: =IF(C8="","",IF(C8>=D8,"No alvo","Abaixo da meta")) | G8: ↑ melhor
A9: Marketing | B9: SQLs gerados | C9: =IFERROR(LOOKUP(2,1/(Semanal!$E$6:$E$21<>""),Semanal!E$6:E$21),"") | D9: =Metas!E6 | E9: =IF(OR(C9="",D9=""),"",C9-D9) | F9: =IF(C9="","",IF(C9>=D9,"No alvo","Abaixo da meta")) | G9: ↑ melhor
A10: Marketing | B10: CPSQL | C10: =IFERROR(LOOKUP(2,1/(Semanal!$E$6:$E$21<>""),Semanal!J$6:J$21),"") | D10: =Metas!E7 | E10: =IF(OR(C10="",D10=""),"",D10-C10) | F10: =IF(C10="","",IF(C10<=D10,"No alvo","Acima da meta")) | G10: ↓ melhor
A11: Marketing | B11: Engajamento | C11: =IFERROR(LOOKUP(2,1/(Semanal!$E$6:$E$21<>""),Semanal!G$6:G$21),"") | D11: =Metas!E8 | E11: =IF(OR(C11="",D11=""),"",C11-D11) | F11: =IF(C11="","",IF(C11>=D11,"No alvo","Abaixo da meta")) | G11: ↑ melhor
A12: Marketing | B12: % acima score | C12: =IFERROR(LOOKUP(2,1/(Semanal!$E$6:$E$21<>""),Semanal!H$6:H$21),"") | D12: =Metas!E9 | E12: =IF(OR(C12="",D12=""),"",C12-D12) | F12: =IF(C12="","",IF(C12>=D12,"No alvo","Abaixo da meta")) | G12: ↑ melhor
A13: Vendas | B13: SQL → Cliente | C13: =IFERROR(LOOKUP(2,1/(Semanal!$E$6:$E$21<>""),Semanal!S$6:S$21),"") | D13: =Metas!E10 | E13: =IF(OR(C13="",D13=""),"",C13-D13) | F13: =IF(C13="","",IF(C13>=D13,"No alvo","Abaixo da meta")) | G13: ↑ melhor
A14: Vendas | B14: Ciclo médio (dias) | C14: =IFERROR(LOOKUP(2,1/(Semanal!$E$6:$E$21<>""),Semanal!M$6:M$21),"") | D14: =Metas!E11 | E14: =IF(OR(C14="",D14=""),"",D14-C14) | F14: =IF(C14="","",IF(C14<=D14,"No alvo","Acima da meta")) | G14: ↓ melhor
A15: Vendas | B15: Ticket médio 1º | C15: =IFERROR(LOOKUP(2,1/(Semanal!$E$6:$E$21<>""),Semanal!N$6:N$21),"") | D15: =Metas!E12 | E15: =IF(OR(C15="",D15=""),"",C15-D15) | F15: =IF(C15="","",IF(C15>=D15,"No alvo","Abaixo da meta")) | G15: ↑ melhor
A16: Vendas | B16: Win rate | C16: =IFERROR(LOOKUP(2,1/(Semanal!$E$6:$E$21<>""),Semanal!T$6:T$21),"") | D16: =Metas!E13 | E16: =IF(OR(C16="",D16=""),"",C16-D16) | F16: =IF(C16="","",IF(C16>=D16,"No alvo","Abaixo da meta")) | G16: ↑ melhor
A17: Vendas | B17: Visitas/deal | C17: =IFERROR(LOOKUP(2,1/(Semanal!$E$6:$E$21<>""),Semanal!U$6:U$21),"") | D17: =Metas!E14 | E17: =IF(OR(C17="",D17=""),"",D17-C17) | F17: =IF(C17="","",IF(C17<=D17,"No alvo","Acima da meta")) | G17: ↓ melhor
A18: Vendas | B18: Cobertura pipeline | C18: =IFERROR(LOOKUP(2,1/(Semanal!$E$6:$E$21<>""),Semanal!V$6:V$21),"") | D18: =Metas!E15 | E18: =IF(OR(C18="",D18=""),"",C18-D18) | F18: =IF(C18="","",IF(C18>=D18,"No alvo","Abaixo da meta")) | G18: ↑ melhor
A19: Ponte | B19: Aceite de SQL | C19: =IFERROR(LOOKUP(2,1/(Semanal!$E$6:$E$21<>""),Semanal!AB$6:AB$21),"") | D19: =Metas!E16 | E19: =IF(OR(C19="",D19=""),"",C19-D19) | F19: =IF(C19="","",IF(C19>=D19,"No alvo","Abaixo da meta")) | G19: ↑ melhor
A20: Ponte | B20: SLA 1º contato (h) | C20: =IFERROR(LOOKUP(2,1/(Semanal!$E$6:$E$21<>""),Semanal!Y$6:Y$21),"") | D20: =Metas!E17 | E20: =IF(OR(C20="",D20=""),"",D20-C20) | F20: =IF(C20="","",IF(C20<=D20,"No alvo","Acima da meta")) | G20: ↓ melhor
A21: Ponte | B21: % c/ motivo perda | C21: =IFERROR(LOOKUP(2,1/(Semanal!$E$6:$E$21<>""),Semanal!AC$6:AC$21),"") | D21: =Metas!E18 | E21: =IF(OR(C21="",D21=""),"",C21-D21) | F21: =IF(C21="","",IF(C21>=D21,"No alvo","Abaixo da meta")) | G21: ↑ melhor
A24: North Stars — foco do ritual
A25: Marketing | B25: MQL → SQL | C25: =C8 | D25: ="Meta: "&TEXT(D8,"0%")
A26: Vendas | B26: SQL → Cliente | C26: =C13 | D26: ="Meta: "&TEXT(D13,"0%")
A27: Ponte | B27: Aceite de SQL | C27: =C19 | D27: ="Meta: "&TEXT(D19,"0%")
A30: Checklist do ritual semanal (30 min)
A31: 1. Olhar Aceite de SQL — subiu ou caiu? Por quê?
A32: 2. Olhar SLA de contato — quem ficou parado > 24h?
A33: 3. Olhar motivos de perda — o que muda na nutrição / ICP?
A34: 4. Registrar decisão e dono na coluna Observações (aba Semanal)
A37: Série — North Stars (preenchido via Semanal)
A38: Início | B38: MQL→SQL | C38: SQL→Cliente | D38: Aceite SQL
A39: =Semanal!B14 | B39: =Semanal!I14 | C39: =Semanal!S14 | D39: =Semanal!AB14
A40: =Semanal!B15 | B40: =Semanal!I15 | C40: =Semanal!S15 | D40: =Semanal!AB15
A41: =Semanal!B16 | B41: =Semanal!I16 | C41: =Semanal!S16 | D41: =Semanal!AB16
A42: =Semanal!B17 | B42: =Semanal!I17 | C42: =Semanal!S17 | D42: =Semanal!AB17
A43: =Semanal!B18 | B43: =Semanal!I18 | C43: =Semanal!S18 | D43: =Semanal!AB18
A44: =Semanal!B19 | B44: =Semanal!I19 | C44: =Semanal!S19 | D44: =Semanal!AB19
A45: =Semanal!B20 | B45: =Semanal!I20 | C45: =Semanal!S20 | D45: =Semanal!AB20
A46: =Semanal!B21 | B46: =Semanal!I21 | C46: =Semanal!S21 | D46: =Semanal!AB21

Sheet Metas
A1: Metas dos KPIs
A2: Edite apenas as células amarelas. As metas alimentam o Dashboard.
A4: Área | B4: KPI | C4: Código | D4: Unidade | E4: Meta | F4: Notas
A5: Marketing | B5: MQL → SQL | C5: MKT_MQL_SQL | D5: % | E5: 0.4 | F5: North Star Marketing
A6: Marketing | B6: SQLs gerados / semana | C6: MKT_SQL_SEM | D6: unid | E6: 8 | F6: Ajuste à capacidade do time
A7: Marketing | B7: Custo por SQL (CPSQL) | C7: MKT_CPSQL | D7: R$ | E7: 350 | F7: Meta máxima (quanto menor, melhor)
A8: Marketing | B8: Engajamento da sequência | C8: MKT_ENG | D8: % | E8: 0.25 | F8: Abriu+clicou ou respondeu
A9: Marketing | B9: % leads acima do score | C9: MKT_SCORE | D9: % | E9: 0.35 | F9: Limiar de intenção definido no CRM
A10: Vendas | B10: SQL → Cliente | C10: VND_SQL_CLI | D10: % | E10: 0.3 | F10: North Star Vendas
A11: Vendas | B11: Ciclo médio de vendas | C11: VND_CICLO | D11: dias | E11: 45 | F11: Meta máxima (quanto menor, melhor)
A12: Vendas | B12: Ticket médio 1º pedido | C12: VND_TICKET | D12: R$ | E12: 15000 | F12: Ajuste ao portfólio
A13: Vendas | B13: Win rate de propostas | C13: VND_WIN | D13: % | E13: 0.45
A14: Vendas | B14: Visitas por deal fechado | C14: VND_VISITAS | D14: unid | E14: 2 | F14: Meta máxima
A15: Vendas | B15: Cobertura de pipeline | C15: VND_PIPE | D15: x | E15: 3 | F15: Pipeline ÷ meta do período
A16: Ponte | B16: Taxa de aceite de SQL | C16: PNT_ACEITE | D16: % | E16: 0.8 | F16: North Star da ponte
A17: Ponte | B17: Tempo até 1º contato | C17: PNT_SLA | D17: horas | E17: 24 | F17: Meta máxima (SLA)
A18: Ponte | B18: SQLs com motivo de perda | C18: PNT_MOTIVO | D18: % | E18: 1 | F18: 100% dos perdidos com motivo no CRM
A20: Meta do faturamento (semana) — usada na cobertura de pipeline | E20: 80000 | F20: Meta semanal de receita (novo + recorrente ou só 1º pedido — alinhe com o time)

Sheet Semanal
A1: Registro Semanal de KPIs
A2: Preencha inputs em azul. Fórmulas em preto calculam automaticamente. Uma linha = uma semana.
A4: Período | D4: MARKETING | K4: VENDAS | W4: PONTE Mkt → Vendas | AD4: Ritual
A5: Semana | B5: Início | C5: Fim | D5: MQLs | E5: SQLs gerados | F5: Investimento (R$) | G5: Engajamento % | H5: % acima score | I5: MQL→SQL % | J5: CPSQL (R$) | K5: SQLs trabalhados | L5: Clientes novos | M5: Ciclo médio (dias) | N5: Ticket médio 1º (R$) | O5: Propostas enviadas | P5: Propostas ganhas | Q5: Visitas | R5: Pipeline (R$) | S5: SQL→Cliente % | T5: Win rate % | U5: Visitas/deal | V5: Cobertura (x) | W5: SQLs enviados | X5: SQLs aceitos | Y5: SLA 1º contato (h) | Z5: SQLs perdidos | AA5: Perdidos c/ motivo | AB5: Aceite SQL % | AC5: % c/ motivo perda | AD5: Observações do ritual | AE5: Responsável
A6: 1 | B6: 46111 | C6: =B6+6 | I6: =IF(D6=0,"",E6/D6) | J6: =IF(E6=0,"",F6/E6) | S6: =IF(K6=0,"",L6/K6) | T6: =IF(O6=0,"",P6/O6) | U6: =IF(L6=0,"",Q6/L6) | V6: =IF(OR(R6="",Metas!$E$20=0),"",R6/Metas!$E$20) | AB6: =IF(W6=0,"",X6/W6) | AC6: =IF(Z6=0,"",AA6/Z6)
A7: 2 | B7: 46118 | C7: =B7+6 | I7: =IF(D7=0,"",E7/D7) | J7: =IF(E7=0,"",F7/E7) | S7: =IF(K7=0,"",L7/K7) | T7: =IF(O7=0,"",P7/O7) | U7: =IF(L7=0,"",Q7/L7) | V7: =IF(OR(R7="",Metas!$E$20=0),"",R7/Metas!$E$20) | AB7: =IF(W7=0,"",X7/W7) | AC7: =IF(Z7=0,"",AA7/Z7)
A8: 3 | B8: 46125 | C8: =B8+6 | I8: =IF(D8=0,"",E8/D8) | J8: =IF(E8=0,"",F8/E8) | S8: =IF(K8=0,"",L8/K8) | T8: =IF(O8=0,"",P8/O8) | U8: =IF(L8=0,"",Q8/L8) | V8: =IF(OR(R8="",Metas!$E$20=0),"",R8/Metas!$E$20) | AB8: =IF(W8=0,"",X8/W8) | AC8: =IF(Z8=0,"",AA8/Z8)
A9: 4 | B9: 46132 | C9: =B9+6 | I9: =IF(D9=0,"",E9/D9) | J9: =IF(E9=0,"",F9/E9) | S9: =IF(K9=0,"",L9/K9) | T9: =IF(O9=0,"",P9/O9) | U9: =IF(L9=0,"",Q9/L9) | V9: =IF(OR(R9="",Metas!$E$20=0),"",R9/Metas!$E$20) | AB9: =IF(W9=0,"",X9/W9) | AC9: =IF(Z9=0,"",AA9/Z9)
A10: 5 | B10: 46139 | C10: =B10+6 | I10: =IF(D10=0,"",E10/D10) | J10: =IF(E10=0,"",F10/E10) | S10: =IF(K10=0,"",L10/K10) | T10: =IF(O10=0,"",P10/O10) | U10: =IF(L10=0,"",Q10/L10) | V10: =IF(OR(R10="",Metas!$E$20=0),"",R10/Metas!$E$20) | AB10: =IF(W10=0,"",X10/W10) | AC10: =IF(Z10=0,"",AA10/Z10)
A11: 6 | B11: 46146 | C11: =B11+6 | I11: =IF(D11=0,"",E11/D11) | J11: =IF(E11=0,"",F11/E11) | S11: =IF(K11=0,"",L11/K11) | T11: =IF(O11=0,"",P11/O11) | U11: =IF(L11=0,"",Q11/L11) | V11: =IF(OR(R11="",Metas!$E$20=0),"",R11/Metas!$E$20) | AB11: =IF(W11=0,"",X11/W11) | AC11: =IF(Z11=0,"",AA11/Z11)
A12: 7 | B12: 46153 | C12: =B12+6 | I12: =IF(D12=0,"",E12/D12) | J12: =IF(E12=0,"",F12/E12) | S12: =IF(K12=0,"",L12/K12) | T12: =IF(O12=0,"",P12/O12) | U12: =IF(L12=0,"",Q12/L12) | V12: =IF(OR(R12="",Metas!$E$20=0),"",R12/Metas!$E$20) | AB12: =IF(W12=0,"",X12/W12) | AC12: =IF(Z12=0,"",AA12/Z12)
A13: 8 | B13: 46160 | C13: =B13+6 | I13: =IF(D13=0,"",E13/D13) | J13: =IF(E13=0,"",F13/E13) | S13: =IF(K13=0,"",L13/K13) | T13: =IF(O13=0,"",P13/O13) | U13: =IF(L13=0,"",Q13/L13) | V13: =IF(OR(R13="",Metas!$E$20=0),"",R13/Metas!$E$20) | AB13: =IF(W13=0,"",X13/W13) | AC13: =IF(Z13=0,"",AA13/Z13)
A14: 9 | B14: 46167 | C14: =B14+6 | I14: =IF(D14=0,"",E14/D14) | J14: =IF(E14=0,"",F14/E14) | S14: =IF(K14=0,"",L14/K14) | T14: =IF(O14=0,"",P14/O14) | U14: =IF(L14=0,"",Q14/L14) | V14: =IF(OR(R14="",Metas!$E$20=0),"",R14/Metas!$E$20) | AB14: =IF(W14=0,"",X14/W14) | AC14: =IF(Z14=0,"",AA14/Z14)
A15: 10 | B15: 46174 | C15: =B15+6 | I15: =IF(D15=0,"",E15/D15) | J15: =IF(E15=0,"",F15/E15) | S15: =IF(K15=0,"",L15/K15) | T15: =IF(O15=0,"",P15/O15) | U15: =IF(L15=0,"",Q15/L15) | V15: =IF(OR(R15="",Metas!$E$20=0),"",R15/Metas!$E$20) | AB15: =IF(W15=0,"",X15/W15) | AC15: =IF(Z15=0,"",AA15/Z15)
A16: 11 | B16: 46181 | C16: =B16+6 | I16: =IF(D16=0,"",E16/D16) | J16: =IF(E16=0,"",F16/E16) | S16: =IF(K16=0,"",L16/K16) | T16: =IF(O16=0,"",P16/O16) | U16: =IF(L16=0,"",Q16/L16) | V16: =IF(OR(R16="",Metas!$E$20=0),"",R16/Metas!$E$20) | AB16: =IF(W16=0,"",X16/W16) | AC16: =IF(Z16=0,"",AA16/Z16)
A17: 12 | B17: 46188 | C17: =B17+6 | I17: =IF(D17=0,"",E17/D17) | J17: =IF(E17=0,"",F17/E17) | S17: =IF(K17=0,"",L17/K17) | T17: =IF(O17=0,"",P17/O17) | U17: =IF(L17=0,"",Q17/L17) | V17: =IF(OR(R17="",Metas!$E$20=0),"",R17/Metas!$E$20) | AB17: =IF(W17=0,"",X17/W17) | AC17: =IF(Z17=0,"",AA17/Z17)
... A20: 15 | B20: 46209 | C20: =B20+6 | I20: =IF(D20=0,"",E20/D20) | J20: =IF(E20=0,"",F20/E20) | S20: =IF(K20=0,"",L20/K20) | T20: =IF(O20=0,"",P20/O20) | U20: =IF(L20=0,"",Q20/L20) | V20: =IF(OR(R20="",Metas!$E$20=0),"",R20/Metas!$E$20) | AB20: =IF(W20=0,"",X20/W20) | AC20: =IF(Z20=0,"",AA20/Z20)
A21: 16 | B21: 46216 | C21: =B21+6 | D21: 22 | E21: 9 | F21: 2800 | G21: 0.28 | H21: 0.41 | I21: =IF(D21=0,"",E21/D21) | J21: =IF(E21=0,"",F21/E21) | K21: 9 | L21: 3 | M21: 38 | N21: 18500 | O21: 7 | P21: 3 | Q21: 5 | R21: 240000 | S21: =IF(K21=0,"",L21/K21) | T21: =IF(O21=0,"",P21/O21) | U21: =IF(L21=0,"",Q21/L21) | V21: =IF(OR(R21="",Metas!$E$20=0),"",R21/Metas!$E$20) | W21: 9 | X21: 8 | Y21: 18 | Z21: 2 | AA21: 2 | AB21: =IF(W21=0,"",X21/W21) | AC21: =IF(Z21=0,"",AA21/Z21) | AD21: Aceite ok. 1 SQL devolvido: lojista fora do ICP. Ajustar scoring. | AE21: Time comercial
